phonevalidatorGCC/__init__.py
phonevalidatorGCC/fields.py
phonevalidatorGCC/strategies/__init__.py
phonevalidatorGCC/strategies/bahrain.py
phonevalidatorGCC/strategies/base.py
phonevalidatorGCC/strategies/egypt.py
phonevalidatorGCC/strategies/kuwait.py
phonevalidatorGCC/strategies/oman.py
phonevalidatorGCC/strategies/qatar.py
phonevalidatorGCC/strategies/saudi.py
phonevalidatorGCC/strategies/uae.py
phonevalidatorGCC/validateDesign/__init__.py
phonevalidatorGCC/validateDesign/decorators.py
phonevalidatorGCC/validateDesign/factory.py
phonevalidatorGCC/validateDesign/observers.py
phonevalidatorGCC/validateDesign/validator.py
Django_GCC_PhoneNumbers-0.0.3.dist-info/METADATA
Django_GCC_PhoneNumbers-0.0.3.dist-info/WHEEL
Django_GCC_PhoneNumbers-0.0.3.dist-info/top_level.txt
Django_GCC_PhoneNumbers-0.0.3.dist-info/RECORD
