Metadata-Version: 2.2
Name: Django_GCC_PhoneNumbers
Version: 0.0.3
Summary: A flexible and extensible phone number validation package for GCC countries and Egypt.
Home-page: https://github.com/Moataz0000/Django-Phone-Number-Field-GCC
Author: Moataz Fawzy
Author-email: motazfawzy73@gmail.com
Classifier: Framework :: Django
Classifier: Programming Language :: Python :: 3
Classifier: License :: OSI Approved :: MIT License
Classifier: Operating System :: OS Independent
Requires-Python: >=3.6
Requires-Dist: Django>=3.0
Dynamic: author
Dynamic: author-email
Dynamic: classifier
Dynamic: description
Dynamic: description-content-type
Dynamic: home-page
Dynamic: requires-dist
Dynamic: requires-python
Dynamic: summary
